drifactorial/__init__.py
drifactorial/schemas.py
drifactorial-0.3.2.dist-info/LICENSE
drifactorial-0.3.2.dist-info/WHEEL
drifactorial-0.3.2.dist-info/METADATA
drifactorial-0.3.2.dist-info/RECORD
