Metadata-Version: 2.1
Name: drifactorial
Version: 0.3.2
Summary: Python client for the Factorial API.
Home-page: https://dribia.github.io/drifactorial
License: MIT
Author: Dribia Data Research
Author-email: opensource@dribia.com
Maintainer: Xavier Hoffmann
Maintainer-email: xrhoffmann@gmail.com
Requires-Python: >=3.6.2,<4.0
Classifier: License :: OSI Approved :: MIT License
Classifier: Programming Language :: Python :: 3
Classifier: Programming Language :: Python :: 3.10
Classifier: Programming Language :: Python :: 3.7
Classifier: Programming Language :: Python :: 3.8
Classifier: Programming Language :: Python :: 3.9
Requires-Dist: importlib-metadata (>=4.6.3,<5.0.0); python_version < "3.8"
Requires-Dist: pydantic (>=1.8.2,<2.0.0)
Project-URL: Documentation, https://dribia.github.io/drifactorial
Project-URL: Repository, https://github.com/dribia/drifactorial
